AUTHORS
CHANGES
LICENSE
MANIFEST.in
README.rst
setup.py
__ereports/__init__.py
__ereports/admin.py
__ereports/context_processors.py
__ereports/exceptions.py
__ereports/math.py
__ereports/models.py
__ereports/postprocessor.py
__ereports/template_loaders.py
__ereports/tests.py
__ereports/urls.py
__ereports/views.py
__ereports/templatetags/__init__.py
__ereports/templatetags/ereports.py
__ereports/tests/__init__.py
__ereports/tests/settings.py
__ereports/tests/urls.py
django_easy_reports.egg-info/PKG-INFO
django_easy_reports.egg-info/SOURCES.txt
django_easy_reports.egg-info/dependency_links.txt
django_easy_reports.egg-info/requires.txt
django_easy_reports.egg-info/top_level.txt
ereports/__init__.py
ereports/admin.py
ereports/filtering.py
ereports/forms.py
ereports/models.py
ereports/template_loaders.py
ereports/urls.py
ereports/utils.py
ereports/views.py
ereports/engine/__init__.py
ereports/engine/cache.py
ereports/engine/columns.py
ereports/engine/config.py
ereports/engine/datasource.py
ereports/engine/exceptions.py
ereports/engine/mixins.py
ereports/engine/registry.py
ereports/engine/renderer.py
ereports/engine/report.py
ereports/engine/utils.py
ereports/engine/widgets.py
ereports/management/__init__.py
ereports/management/commands/__init__.py
ereports/management/commands/register_report.py
ereports/migrations/0001_initial.py
ereports/migrations/0002_auto__chg_field_reportconfiguration_description.py
ereports/migrations/__init__.py
ereports/requirements/install.pip
ereports/requirements/testing.pip
ereports/static/ereports/css/ereport.css
ereports/static/ereports/css/ereport.min.css
ereports/static/ereports/css/ereport.min.min.css
ereports/static/ereports/css/report.css
ereports/static/ereports/css/report.min.css
ereports/static/ereports/css/report.min.min.css
ereports/static/ereports/js/jquery-1.5.1.min.js
ereports/static/ereports/js/jquery-1.5.1.min.min.js
ereports/static/ereports/js/jquery-ui-1.8.10.min.js
ereports/static/ereports/js/jquery-ui-1.8.10.min.min.js
ereports/static/ereports/multiselect/css/common.css
ereports/static/ereports/multiselect/css/common.min.css
ereports/static/ereports/multiselect/css/common.min.min.css
